beacon_binary_format-3.0.0a0.dist-info/METADATA
beacon_binary_format-3.0.0a0.dist-info/WHEEL
beacon_binary_format-3.0.0a0.dist-info/licenses/LICENSE
beacon_binary_format.pyi
beacon_binary_format/__init__.py
beacon_binary_format/__init__.pyi
beacon_binary_format/beacon_binary_format.cpython-311-x86_64-linux-gnu.so
beacon_binary_format/py.typed
py.typed
beacon_binary_format-3.0.0a0.dist-info/RECORD
