Metadata-Version: 2.4
Name: beacon-binary-format
Version: 3.0.0a0
Classifier: Programming Language :: Rust
Classifier: Programming Language :: Python
Classifier: Programming Language :: Python :: 3
Classifier: Operating System :: OS Independent
Requires-Dist: numpy>=1.24
Requires-Dist: fsspec>=2023.1.0
License-File: LICENSE
Summary: Python bindings for the Beacon Binary Format collection writer.
Keywords: ocean,arrow,beacon,bbf
Requires-Python: >=3.10
